odoo/addons/l10n_mx_pms/README.rst
odoo/addons/l10n_mx_pms/__init__.py
odoo/addons/l10n_mx_pms/__manifest__.py
odoo/addons/l10n_mx_pms/i18n/es.po
odoo/addons/l10n_mx_pms/i18n/l10n_mx_pms.pot
odoo/addons/l10n_mx_pms/readme/CONTRIBUTORS.rst
odoo/addons/l10n_mx_pms/readme/CREDITS.rst
odoo/addons/l10n_mx_pms/readme/DESCRIPTION.rst
odoo/addons/l10n_mx_pms/static/description/icon.png
odoo/addons/l10n_mx_pms/static/description/index.html
odoo/addons/l10n_mx_pms/views/pms_property.xml
odoo14_addon_l10n_mx_pms-14.0.1.0.1.dev4.dist-info/METADATA
odoo14_addon_l10n_mx_pms-14.0.1.0.1.dev4.dist-info/WHEEL
odoo14_addon_l10n_mx_pms-14.0.1.0.1.dev4.dist-info/top_level.txt
odoo14_addon_l10n_mx_pms-14.0.1.0.1.dev4.dist-info/RECORD
